realtime_results/__init__.py
realtime_results/main.py
realtime_results/repository/__init__.py
realtime_results/repository/redis_conn.py
realtime_results_module-0.0.4.dist-info/METADATA
realtime_results_module-0.0.4.dist-info/WHEEL
realtime_results_module-0.0.4.dist-info/top_level.txt
realtime_results_module-0.0.4.dist-info/RECORD
