Metadata-Version: 2.1
Name: realtime-results-module
Version: 0.0.4
Summary: Wrapper for realtime results
Home-page: https://mnc-repo.mncdigital.com/ai-team/vision_plus/rce_realtime_results_module
Author: AI Teams
Author-email: ferdina.kusumah@mncgroup.com
License: MIT
Platform: UNKNOWN
Classifier: License :: OSI Approved :: MIT License
Classifier: Programming Language :: Python :: 3
Classifier: Programming Language :: Python :: 3.7
Classifier: Programming Language :: Python :: 3.8
Classifier: Programming Language :: Python :: 3.9
Requires-Dist: graphdb-module (==0.3.3)
Requires-Dist: redis (==4.2.2)
